{"result": {"took": 5328, "timed_out": false, "_shards": {"total": 5, "successful": 5, "skipped": 0, "failed": 0}, "hits": {"total": 1, "max_score": 0.0, "hits": [{"_index": "commoncrawl", "_type": "sentence", "_id": "147067984", "_score": 0.0, "_source": {"text": "A deluge a few hours before kick-off left the San Siro pitch resembling a bog, but Meazza, who knew this ground better than anybody on the Italian team, made light of the conditions to book his country's place in the final."}, "highlight": {"text": ["A **deluge** a few hours before **kick**-off left the San Siro pitch resembling a bog, but Meazza, who knew", " this ground **better** **than** anybody on the Italian team, made light of the conditions to book his country's place in the final."]}}]}}}