[{"uri":"http://dbpedia.org/property/homeQtr","label":"home qtr"},{"uri":"http://dbpedia.org/property/womens","label":"womens"},{"uri":"http://dbpedia.org/property/next","label":"next"},{"uri":"http://dbpedia.org/property/rd1Team","label":"RD1-team"},{"uri":"http://dbpedia.org/property/visitorTotal","label":"visitor total"},{"uri":"http://dbpedia.org/property/rd3Team","label":"RD3-team"},{"uri":"http://dbpedia.org/property/relegation","label":"relegation"},{"uri":"http://dbpedia.org/property/stadium","label":"stadium"},{"uri":"http://dbpedia.org/property/sports","label":"sports"},{"uri":"http://dbpedia.org/property/rd3Seed","label":"RD3-seed"},{"uri":"http://dbpedia.org/property/headquarters","label":"headquarters"},{"uri":"http://dbpedia.org/property/upcomingSeason","label":"upcoming season"},{"uri":"http://dbpedia.org/property/reason","label":"reason"},{"uri":"http://dbpedia.org/property/chairman","label":"chairman"},{"uri":"http://dbpedia.org/property/owner","label":"owner"},{"uri":"http://dbpedia.org/property/hqStateabb","label":"hq stateabb"},{"uri":"http://dbpedia.org/property/promotion","label":"promotion"},{"uri":"http://dbpedia.org/property/fixAttempted","label":"fix-attempted"},{"uri":"http://dbpedia.org/property/logoSize","label":"logo size"},{"uri":"http://dbpedia.org/property/formerNames","label":"former names"},{"uri":"http://dbpedia.org/property/visitorAbbr","label":"visitor abbr"},{"uri":"http://dbpedia.org/property/home","label":"Home"},{"uri":"http://dbpedia.org/property/recentChamps","label":"recent champs"},{"uri":"http://dbpedia.org/property/rd1Score","label":"RD1-score"},{"uri":"http://dbpedia.org/property/pixels","label":"pixels"},{"uri":"http://dbpedia.org/property/founder","label":"founder"},{"uri":"http://dbpedia.org/property/visitorConf","label":"visitor conf"},{"uri":"http://dbpedia.org/property/float","label":"float"},{"uri":"http://dbpedia.org/property/date","label":"date"},{"uri":"http://dbpedia.org/property/division","label":"division"},{"uri":"http://dbpedia.org/property/rd2Score","label":"RD2-score"},{"uri":"http://dbpedia.org/property/dissolved","label":"dissolved"},{"uri":"http://dbpedia.org/property/hqState","label":"hq state"},{"uri":"http://dbpedia.org/property/state","label":"state"},{"uri":"http://dbpedia.org/property/founded","label":"founded"},{"uri":"http://dbpedia.org/property/rd1Seed","label":"RD1-seed"},{"uri":"http://dbpedia.org/property/countries","label":"countries"},{"uri":"http://dbpedia.org/property/last","label":"last"},{"uri":"http://dbpedia.org/property/fame","label":"fame"},{"uri":"http://dbpedia.org/property/teams","label":"teams"},{"uri":"http://dbpedia.org/property/logo","label":"logo"},{"uri":"http://dbpedia.org/property/visitor","label":"visitor"},{"uri":"http://dbpedia.org/property/homeTotal","label":"home total"},{"uri":"http://dbpedia.org/property/folded","label":"folded"},{"uri":"http://dbpedia.org/property/shortName","label":"short name"},{"uri":"http://dbpedia.org/property/commissioner","label":"commissioner"},{"uri":"http://dbpedia.org/property/venue","label":"venue"},{"uri":"http://dbpedia.org/property/rd2Team","label":"RD2-team"},{"uri":"http://dbpedia.org/property/title","label":"title"},{"uri":"http://dbpedia.org/property/subdivision","label":"subdivision"},{"uri":"http://dbpedia.org/property/association","label":"Association"},{"uri":"http://dbpedia.org/property/author","label":"author"},{"uri":"http://dbpedia.org/property/homeAbbr","label":"home abbr"},{"uri":"http://dbpedia.org/property/scale","label":"scale"},{"uri":"http://dbpedia.org/property/mapSize","label":"map size"},{"uri":"http://dbpedia.org/property/color","label":"color"},{"uri":"http://dbpedia.org/property/name","label":"name"},{"uri":"http://dbpedia.org/property/rd2Seed","label":"RD2-seed"},{"uri":"http://dbpedia.org/property/hqCity","label":"hq city"},{"uri":"http://dbpedia.org/property/continent","label":"continent"},{"uri":"http://dbpedia.org/property/visitorQtr","label":"visitor qtr"},{"uri":"http://dbpedia.org/property/members","label":"members"},{"uri":"http://dbpedia.org/property/director","label":"director"},{"uri":"http://dbpedia.org/property/established","label":"established"},{"uri":"http://dbpedia.org/property/fate","label":"fate"},{"uri":"http://dbpedia.org/property/city","label":"city"},{"uri":"http://dbpedia.org/property/colour","label":"colour"},{"uri":"http://dbpedia.org/property/president","label":"President"},{"uri":"http://dbpedia.org/property/website","label":"Website"},{"uri":"http://dbpedia.org/property/fontColor","label":"font color"},{"uri":"http://dbpedia.org/property/sport","label":"sport"},{"uri":"http://dbpedia.org/property/homeConf","label":"home conf"},{"uri":"http://dbpedia.org/property/mens","label":"mens"},{"uri":"http://dbpedia.org/property/levels","label":"levels"},{"uri":"http://dbpedia.org/property/formerly","label":"formerly"},{"uri":"http://dbpedia.org/property/lastSeason","label":"last season"},{"uri":"http://dbpedia.org/property/mostChamps","label":"most champs"},{"uri":"http://dbpedia.org/property/width","label":"width"},{"uri":"http://dbpedia.org/property/text","label":"text"},{"uri":"http://dbpedia.org/property/champion","label":"champion"},{"uri":"http://dbpedia.org/property/relatedComps","label":"related comps"},{"uri":"http://dbpedia.org/property/country","label":"country"},{"uri":"http://dbpedia.org/property/type","label":"type"},{"uri":"http://dbpedia.org/property/road","label":"Road"},{"uri":"http://dbpedia.org/property/rd3Score","label":"RD3-score"},{"uri":"http://dbpedia.org/property/region","label":"region"},{"uri":"http://dbpedia.org/property/league","label":"league"},{"uri":"http://dbpedia.org/property/caption","label":"Caption"},{"uri":"http://dbpedia.org/property/since","label":"since"},{"uri":"http://dbpedia.org/property/history","label":"history"},{"uri":"http://dbpedia.org/property/slogan","label":"Slogan"}]