{"result": {"took": 4151, "timed_out": false, "_shards": {"total": 5, "successful": 5, "skipped": 0, "failed": 0}, "hits": {"total": 1, "max_score": 0.0, "hits": [{"_index": "commoncrawl", "_type": "sentence", "_id": "161667017", "_score": 0.0, "_source": {"text": "After Blake Griffin, I'm betting Cousins is next most likely to win ROY, so I'm glad that you think Cousins will be better than projected using your models (third would be John Wall, but not due to productivity)."}, "highlight": {"text": [" Cousins will be **better** **than** projected using your models (third would be **John** **Wall**, but not due to productivity).", "After Blake Griffin, I'm betting Cousins is **next** most likely to win ROY, so I'm glad that you think"]}}]}}}