{"took": 2963, "timed_out": false, "_shards": {"total": 5, "successful": 5, "skipped": 0, "failed": 0}, "hits": {"total": 2, "max_score": 0.0, "hits": [{"_index": "commoncrawl", "_type": "sentence", "_id": "129263582", "_score": 0.0, "_source": {"text": "According to the New York Times and the Asian Wall Street Journal, Apple initially said that the ad was being pulled because the company wanted to depict someone better known in the region than the Dalai Lama -- a comment that apparently was met with skepticism given that the Asian ad campaign will feature a photo of US aviator Amelia Earhart, whose plane disappeared in the Pacific Ocean in 1937."}, "highlight": {"text": [" was being pulled **because** **the** **company** wanted to depict someone **better** **known** in the region than the", "According to the **New** **York** Times and the Asian Wall Street Journal, Apple initially said that the ad"]}}, {"_index": "commoncrawl", "_type": "sentence", "_id": "104597232", "_score": 0.0, "_source": {"text": "8/30/06 EMILY I THINK THAT MEXICANS DONT TAKE THE JOBS AWAY BECAUSE FIRST OF ALL I NEVER SEE A MEXICAN (IMMAGRANT) BE A DOCTOR I SEE THEM WORKING AT TACO BELL FOR A BETTER LIFE OK AND OTHER PEOPLE SAY THAT MEXICANS ARE HERE WASTING THEIR TIME BUT YOU KNOW WHAT OTHERS DONT AND I THINK THE SAME THINGS ABOUT THE PEOPLE THAT LIVE HERE AND THAT WERE BORN HERE SO GET A LFE 6/26/06 8/21/06 Las Vegas, NV I thoroughly enjoyed the program \"The New Americans\"."}, "highlight": {"text": ["8/30/06 EMILY I THINK THAT MEXICANS DONT TAKE THE JOBS **AWAY** **BECAUSE** FIRST OF ALL I NEVER SEE A", " MEXICAN (IMMAGRANT) BE A DOCTOR I SEE THEM WORKING AT TACO BELL FOR A **BETTER** **LIFE** OK AND OTHER PEOPLE", " I thoroughly enjoyed **the** **program** \"The New Americans\"."]}}]}}